{
    "def": {
        "prefix": "def",
        "body" : [
            "def ${1:function}(${2:para}):",
            "  $0",
            "end"
        ],
        "description": "declare a new method"
    },
    "if": {
        "prefix": "if",
        "body": [
            "if (${1:expression}):",
            "  $0",
            "end"
        ],
        "description": "if-statement"
    },
    "elif": {
        "prefix": "elif",
        "body": [
            "elif (${1:expression}):",
            "  $0"
        ],
        "description": "else-if-statement"
    },
    "else": {
        "prefix": "else",
        "body": [
            "else:",
            "  $0"
        ],
        "description": "else-statement"
    },
    "while": {
        "prefix": "while",
        "body": [
            "while ${1:i} ${2|<,>,<=,>=,==|} ${3:value}:",
            "  $0",
            "end"
        ],
        "description": "while-loops"
    },
    "thread": {
        "prefix": "thread",
        "body": [
            "thread ${1:thread_name}():",
            "  $0",
            "end"
        ],
        "description": "declare a new thread"
    },
    "global": {
        "prefix": "global",
        "body": [
            "global ${1:variable}$0"
        ],
        "description": "declare a global variable"
    },
    "true": {
        "prefix": "True",
        "body": [
            "True"
        ],
        "description": "autofill a 'True' sign"
    },
    "false": {
        "prefix": "False",
        "body": [
            "False"
        ],
        "description": "autofill a 'False' sign"
    }
}